{"vols":[{"Date": "2020-06-19", "Aeronef": "F-BSPS", "RFID": "ICA3849F2", "Deco": "09:13:15", "Atterro": "09:18:21", "Mode": "S", "HautLarg": null, "Couple": null}, {"Date": "2020-06-19", "Aeronef": "F-BSPS", "RFID": "ICA3849F2", "Deco": "09:23:14", "Atterro": "09:42:24", "Mode": "S", "HautLarg": null, "Couple": null}, {"Date": "2020-06-19", "Aeronef": "F-BSPS", "RFID": "ICA3849F2", "Deco": "09:42:39", "Atterro": "09:49:25", "Mode": "S", "HautLarg": null, "Couple": null}, {"Date": "2020-06-19", "Aeronef": "X-00005", "RFID": "ICA38E65C", "Deco": "13:04:24", "Atterro": "13:04:24", "Mode": "X", "HautLarg": null, "Couple": null}, {"Date": "2020-06-19", "Aeronef": "F-CEAF", "RFID": "FLRDD83CE", "Deco": "13:28:55", "Atterro": "13:34:08", "Mode": "W", "HautLarg": 1192, "Couple": null}, {"Date": "2020-06-19", "Aeronef": "F-CHBY", "RFID": "FLRDDA308", "Deco": "13:33:49", "Atterro": "13:41:49", "Mode": "W", "HautLarg": 1366, "Couple": null}, {"Date": "2020-06-19", "Aeronef": "F-CDYD", "RFID": "FLRDDA42B", "Deco": "13:39:14", "Atterro": "14:40:57", "Mode": "W", "HautLarg": 965, "Couple": null}, {"Date": "2020-06-19", "Aeronef": "F-CECY", "RFID": "FLRDDA371", "Deco": "13:43:51", "Atterro": "13:49:55", "Mode": "W", "HautLarg": 1354, "Couple": null}, {"Date": "2020-06-19", "Aeronef": "F-JCIN", "RFID": "FLRDD5287", "Deco": "13:53:48", "Atterro": "14:00:23", "Mode": "A", "HautLarg": 1469, "Couple": "FLRDDAECC"}, {"Date": "2020-06-19", "Aeronef": "F-CEAJ", "RFID": "FLRDDAECC", "Deco": "13:53:49", "Atterro": "15:22:12", "Mode": "A", "HautLarg": 1559, "Couple": "FLRDD5287"}, {"Date": "2020-06-19", "Aeronef": "F-CDYA", "RFID": "FLRDD9B73", "Deco": "13:56:05", "Atterro": "14:42:05", "Mode": "W", "HautLarg": 1268, "Couple": null}, {"Date": "2020-06-19", "Aeronef": "F-CLMT", "RFID": "FLRDDA3A2", "Deco": "14:02:02", "Atterro": "15:27:36", "Mode": "W", "HautLarg": 1277, "Couple": null}, {"Date": "2020-06-19", "Aeronef": "F-CEJU", "RFID": "FLRDD4FEA", "Deco": "14:07:18", "Atterro": "14:13:15", "Mode": "W", "HautLarg": 1254, "Couple": null}, {"Date": "2020-06-19", "Aeronef": "F-CEAF", "RFID": "FLRDD83CE", "Deco": "14:12:06", "Atterro": "15:00:05", "Mode": "W", "HautLarg": 1192, "Couple": null}, {"Date": "2020-06-19", "Aeronef": "F-CECY", "RFID": "FLRDDA371", "Deco": "14:23:01", "Atterro": "15:39:32", "Mode": "W", "HautLarg": 1424, "Couple": null}, {"Date": "2020-06-19", "Aeronef": "F-CHBY", "RFID": "FLRDDA308", "Deco": "14:26:54", "Atterro": "15:25:49", "Mode": "W", "HautLarg": 1413, "Couple": null}, {"Date": "2020-06-19", "Aeronef": "F-COKE", "RFID": "FLRDDF01F", "Deco": "14:31:25", "Atterro": "16:53:21", "Mode": "W", "HautLarg": 1510, "Couple": null}, {"Date": "2020-06-19", "Aeronef": "F-CMHN", "RFID": "ICA38E9BB", "Deco": "14:35:51", "Atterro": "16:56:59", "Mode": "W", "HautLarg": 1160, "Couple": null}, {"Date": "2020-06-19", "Aeronef": "F-CFXK", "RFID": "FLRDD9510", "Deco": "14:48:17", "Atterro": "17:09:58", "Mode": "W", "HautLarg": 1508, "Couple": null}, {"Date": "2020-06-19", "Aeronef": "F-CEJU", "RFID": "FLRDD4FEA", "Deco": "14:52:19", "Atterro": "14:52:42", "Mode": null, "HautLarg": 54, "Couple": null}, {"Date": "2020-06-19", "Aeronef": "F-CDYA", "RFID": "FLRDD9B73", "Deco": "15:07:32", "Atterro": "15:07:53", "Mode": null, "HautLarg": 32, "Couple": null}, {"Date": "2020-06-19", "Aeronef": "F-CDYD", "RFID": "FLRDDA42B", "Deco": "15:26:18", "Atterro": "16:21:26", "Mode": "W", "HautLarg": 1302, "Couple": null}, {"Date": "2020-06-19", "Aeronef": "F-CEJU", "RFID": "FLRDD4FEA", "Deco": "15:43:01", "Atterro": "15:43:30", "Mode": null, "HautLarg": 69, "Couple": null}, {"Date": "2020-06-19", "Aeronef": "X-00005", "RFID": "ICA38E65C", "Deco": "15:47:24", "Atterro": "17:26:15", "Mode": null, "HautLarg": 1146, "Couple": null}, {"Date": "2020-06-19", "Aeronef": "F-CEAF", "RFID": "FLRDD83CE", "Deco": "15:53:38", "Atterro": "15:54:13", "Mode": null, "HautLarg": 34, "Couple": null}, {"Date": "2020-06-19", "Aeronef": "F-CDYA", "RFID": "FLRDD9B73", "Deco": "16:02:02", "Atterro": "16:03:38", "Mode": "W", "HautLarg": 503, "Couple": null}, {"Date": "2020-06-19", "Aeronef": "F-CLMT", "RFID": "FLRDDA3A2", "Deco": "16:07:17", "Atterro": "16:08:08", "Mode": "W", "HautLarg": 254, "Couple": null}, {"Date": "2020-06-19", "Aeronef": "F-CHBY", "RFID": "FLRDDA308", "Deco": "16:20:23", "Atterro": "16:42:54", "Mode": "W", "HautLarg": 1174, "Couple": null}, {"Date": "2020-06-19", "Aeronef": "F-JCIN", "RFID": "FLRDD5287", "Deco": "16:24:54", "Atterro": "16:32:04", "Mode": null, "HautLarg": 1384, "Couple": null}, {"Date": "2020-06-19", "Aeronef": "F-CLOE", "RFID": "FLRDDAEDF", "Deco": "16:47:08", "Atterro": "18:07:12", "Mode": "W", "HautLarg": 1497, "Couple": null}, {"Date": "2020-06-19", "Aeronef": "F-CEJU", "RFID": "FLRDD4FEA", "Deco": "16:52:26", "Atterro": "18:24:44", "Mode": "W", "HautLarg": 1271, "Couple": null}, {"Date": "2020-06-19", "Aeronef": "F-CEAF", "RFID": "FLRDD83CE", "Deco": "16:58:42", "Atterro": "18:20:25", "Mode": "W", "HautLarg": 1323, "Couple": null}, {"Date": "2020-06-19", "Aeronef": "F-CDYD", "RFID": "FLRDDA42B", "Deco": "17:15:46", "Atterro": "18:14:31", "Mode": "W", "HautLarg": 1184, "Couple": null}, {"Date": "2020-06-19", "Aeronef": "F-CHBY", "RFID": "FLRDDA308", "Deco": "17:26:37", "Atterro": "17:27:20", "Mode": "W", "HautLarg": 532, "Couple": null}, {"Date": "2020-06-19", "Aeronef": "F-CECY", "RFID": "FLRDDA371", "Deco": "17:35:29", "Atterro": "17:41:34", "Mode": "W", "HautLarg": 1602, "Couple": null}, {"Date": "2020-06-19", "Aeronef": "F-CEAJ", "RFID": "FLRDDAECC", "Deco": "17:59:40", "Atterro": "17:59:40", "Mode": "X", "HautLarg": null, "Couple": null}, {"Date": "2020-06-19", "Aeronef": "F-CHBY", "RFID": "FLRDDA308", "Deco": "18:01:35", "Atterro": "18:54:31", "Mode": "W", "HautLarg": 1655, "Couple": null}, {"Date": "2020-06-19", "Aeronef": "F-CECY", "RFID": "FLRDDA371", "Deco": "18:33:33", "Atterro": "19:05:10", "Mode": "W", "HautLarg": 1216, "Couple": null}, {"Date": "2020-06-19", "Aeronef": "F-CLOE", "RFID": "FLRDDAEDF", "Deco": "18:45:34", "Atterro": "18:57:39", "Mode": "W", "HautLarg": 1489, "Couple": null}, {"Date": "2020-06-19", "Aeronef": "F-CEAF", "RFID": "FLRDD83CE", "Deco": "18:51:56", "Atterro": "20:08:35", "Mode": "W", "HautLarg": 1271, "Couple": null}, {"Date": "2020-06-19", "Aeronef": "F-CDYD", "RFID": "FLRDDA42B", "Deco": "18:58:59", "Atterro": "19:26:12", "Mode": "W", "HautLarg": 1257, "Couple": null}],"created":"23:58:02"}
